initialterm/__init__.py
initialterm/main.py
initialterm/setup.py
initialterm-0.1.0.dist-info/LICENSE
initialterm-0.1.0.dist-info/METADATA
initialterm-0.1.0.dist-info/WHEEL
initialterm-0.1.0.dist-info/entry_points.txt
initialterm-0.1.0.dist-info/top_level.txt
initialterm-0.1.0.dist-info/RECORD
