Metadata-Version: 2.1
Name: initialterm
Version: 0.1.0
Summary: A human to command-line innterface tool powered by LLM models.
Home-page: https://github.com/sujithhubpost/initialterm
Author: Sujith S
Author-email: sujith@zackriya.com
Classifier: Programming Language :: Python :: 3
Classifier: License :: OSI Approved :: MIT License
Classifier: Operating System :: OS Independent
Requires-Python: >=3.9
License-File: LICENSE
Requires-Dist: ollama
Requires-Dist: requests
